mseep_prometeo_mcp-0.1.1.dist-info/licenses/LICENSE
prometeo_mcp/__init__.py
prometeo_mcp/config.py
prometeo_mcp/mcp_instance.py
prometeo_mcp/server.py
prometeo_mcp/utils.py
mseep_prometeo_mcp-0.1.1.dist-info/METADATA
mseep_prometeo_mcp-0.1.1.dist-info/WHEEL
mseep_prometeo_mcp-0.1.1.dist-info/entry_points.txt
mseep_prometeo_mcp-0.1.1.dist-info/top_level.txt
mseep_prometeo_mcp-0.1.1.dist-info/RECORD
