Metadata-Version: 2.4
Name: mseep-prometeo-mcp
Version: 0.1.1
Summary: Prometeo MCP server interface for testing and integration with LLMs.
Author-email: mseep <support@skydeck.ai>
License: MIT
Requires-Python: >=3.11
License-File: LICENSE
Requires-Dist: pydantic<=2.11
Requires-Dist: mcp[cli]<=1.8.1
Requires-Dist: prometeo==2.0.6
Requires-Dist: python-dotenv<=1.1.0
Requires-Dist: pyyaml<=6.0.2
Provides-Extra: dev
Requires-Dist: pytest>=8.3; extra == "dev"
Requires-Dist: pytest-asyncio>=0.23; extra == "dev"
Requires-Dist: anyio>=4.0; extra == "dev"
Dynamic: license-file
